picamera_mqtt/__init__.py
picamera_mqtt/deploy.py
picamera_mqtt/mqtt_clients.py
picamera_mqtt/protocol.py
picamera_mqtt/imaging/__init__.py
picamera_mqtt/imaging/imaging.py
picamera_mqtt/imaging/mqtt_client_camera.py
picamera_mqtt/imaging/mqtt_client_host.py
picamera_mqtt/tests/__init__.py
picamera_mqtt/tests/imaging/__init__.py
picamera_mqtt/tests/imaging/capture.py
picamera_mqtt/tests/imaging/capture_mock.py
picamera_mqtt/tests/mqtt_clients/__init__.py
picamera_mqtt/tests/mqtt_clients/mock_host.py
picamera_mqtt/tests/mqtt_clients/mock_imaging.py
picamera_mqtt/tests/mqtt_clients/publisher.py
picamera_mqtt/tools/__init__.py
picamera_mqtt/tools/acquire_host.py
picamera_mqtt/tools/mqtt_send_camera_params.py
picamera_mqtt/tools/mqtt_send_deployment.py
picamera_mqtt/tools/timelapse_host.py
picamera_mqtt/util/__init__.py
picamera_mqtt/util/async.py
picamera_mqtt/util/config.py
picamera_mqtt/util/files.py
picamera_mqtt/util/logging.py
picamera_mqtt-0.0.5.dist-info/LICENSE
picamera_mqtt-0.0.5.dist-info/METADATA
picamera_mqtt-0.0.5.dist-info/WHEEL
picamera_mqtt-0.0.5.dist-info/top_level.txt
picamera_mqtt-0.0.5.dist-info/RECORD
