Metadata-Version: 2.1
Name: picamera-mqtt
Version: 0.0.5
Summary: MQTT-based control and image capture with local and remote networked Raspberry Pi cameras.
Home-page: https://github.com/ethanjli/picamera-mqtt
Author: Ethan Li
Author-email: lietk12@gmail.com
License: BSD 3-Clause License
Platform: UNKNOWN
Classifier: Programming Language :: Python :: 3
Classifier: License :: OSI Approved :: BSD License
Classifier: Operating System :: OS Independent
Classifier: Development Status :: 3 - Alpha
Classifier: Topic :: Multimedia :: Graphics :: Capture :: Digital Camera
Requires-Dist: paho-mqtt
Requires-Dist: pillow
Provides-Extra: mock_camera_client
Requires-Dist: numpy ; extra == 'mock_camera_client'
Provides-Extra: picamera_client
Requires-Dist: picamera ; extra == 'picamera_client'
